crimson/tracer/__init__.py
crimson/tracer/filter.py
crimson/tracer/json.py
crimson/tracer/node.py
crimson/tracer/tracer.py
crimson/tracer/example/script.py
crimson_tracer-0.1.5.dist-info/LICENSE
crimson_tracer-0.1.5.dist-info/METADATA
crimson_tracer-0.1.5.dist-info/WHEEL
crimson_tracer-0.1.5.dist-info/top_level.txt
crimson_tracer-0.1.5.dist-info/RECORD
